odoo8_addon_stock_shipment_management-8.0.1.0.2.99.dev3-py2.7-nspkg.pth
odoo8_addon_stock_shipment_management-8.0.1.0.2.99.dev3.dist-info/DESCRIPTION.rst
odoo8_addon_stock_shipment_management-8.0.1.0.2.99.dev3.dist-info/METADATA
odoo8_addon_stock_shipment_management-8.0.1.0.2.99.dev3.dist-info/RECORD
odoo8_addon_stock_shipment_management-8.0.1.0.2.99.dev3.dist-info/WHEEL
odoo8_addon_stock_shipment_management-8.0.1.0.2.99.dev3.dist-info/metadata.json
odoo8_addon_stock_shipment_management-8.0.1.0.2.99.dev3.dist-info/namespace_packages.txt
odoo8_addon_stock_shipment_management-8.0.1.0.2.99.dev3.dist-info/top_level.txt
odoo_addons/stock_shipment_management/README.rst
odoo_addons/stock_shipment_management/__init__.py
odoo_addons/stock_shipment_management/__openerp__.py
odoo_addons/stock_shipment_management/data/shipment_plan_sequence.xml
odoo_addons/stock_shipment_management/model/__init__.py
odoo_addons/stock_shipment_management/model/purchase_order.py
odoo_addons/stock_shipment_management/model/sale_order.py
odoo_addons/stock_shipment_management/model/shipment_plan.py
odoo_addons/stock_shipment_management/model/stock_move.py
odoo_addons/stock_shipment_management/security/ir.model.access.csv
odoo_addons/stock_shipment_management/static/description/icon.png
odoo_addons/stock_shipment_management/tests/__init__.py
odoo_addons/stock_shipment_management/tests/test_shipment_creation.py
odoo_addons/stock_shipment_management/view/menu.xml
odoo_addons/stock_shipment_management/view/purchase_order.xml
odoo_addons/stock_shipment_management/view/sale_order.xml
odoo_addons/stock_shipment_management/view/shipment_plan.xml
odoo_addons/stock_shipment_management/view/stock_move.xml
odoo_addons/stock_shipment_management/wizard/__init__.py
odoo_addons/stock_shipment_management/wizard/create_shipment.py
odoo_addons/stock_shipment_management/wizard/create_shipment_view.xml
odoo_addons/stock_shipment_management/wizard/shipment_carrier_setter.py
odoo_addons/stock_shipment_management/wizard/shipment_carrier_setter_view.xml
odoo_addons/stock_shipment_management/wizard/shipment_carrier_tracking_ref_setter.py
odoo_addons/stock_shipment_management/wizard/shipment_carrier_tracking_ref_setter_view.xml
odoo_addons/stock_shipment_management/wizard/shipment_consignee_setter.py
odoo_addons/stock_shipment_management/wizard/shipment_consignee_setter_view.xml
odoo_addons/stock_shipment_management/wizard/shipment_eta_setter.py
odoo_addons/stock_shipment_management/wizard/shipment_eta_setter_view.xml
