Metadata-Version: 2.0
Name: odoo8-addon-stock-shipment-management
Version: 8.0.1.0.2.99.dev3
Summary: Shipment Management (Consignment)
Home-page: http://www.camptocamp.com
Author: Camptocamp,Odoo Community Association (OCA)
Author-email: support@odoo-community.org
License: AGPL-3
Platform: UNKNOWN
Classifier: Programming Language :: Python
Classifier: Framework :: Odoo
Classifier: License :: OSI Approved :: GNU Affero General Public License v3
Requires-Python: ~=2.7
Requires-Dist: odoo (<9.0a,>=8.0a)
Requires-Dist: odoo8-addon-purchase-transport-multi-address
Requires-Dist: odoo8-addon-sale-transport-multi-address
Requires-Dist: odoo8-addon-stock-route-transit
Requires-Dist: odoo8-addon-transport-information
